gentems/__init__.py
gentems/main.py
gentems-1.0.1.dist-info/LICENSE
gentems-1.0.1.dist-info/METADATA
gentems-1.0.1.dist-info/WHEEL
gentems-1.0.1.dist-info/entry_points.txt
gentems-1.0.1.dist-info/top_level.txt
gentems-1.0.1.dist-info/RECORD
